<?xml version="1.0" encoding="utf-8"?>

<Deployment xmlns="http://schemas.microsoft.com/windowsphone/2012/deployment" AppPlatformVersion="8.0">
  <DefaultLanguage xmlns="" code="en-US"/>
  <App xmlns="" ProductID="{4b228335-9403-4168-80c0-f24157feb608}" Title="StarWars_ListViewWithImages.WinPhone" RuntimeType="Silverlight" Version="1.0.0.0" Genre="apps.normal"  Author="StarWars_ListViewWithImages.WinPhone author" Description="Sample description" Publisher="StarWars_ListViewWithImages.WinPhone" PublisherID="{ff59005d-3e16-4fdb-986f-62a3f67e6d9b}">
    <IconPath IsRelative="true" IsResource="false">Assets\ApplicationIcon.png</IconPath>
    <Capabilities>
      <Capability Name="ID_CAP_NETWORKING"/>
      <Capability Name="ID_CAP_MEDIALIB_AUDIO"/>
      <Capability Name="ID_CAP_MEDIALIB_PLAYBACK"/>
      <Capability Name="ID_CAP_SENSORS"/>
      <Capability Name="ID_CAP_WEBBROWSERCOMPONENT"/>
    </Capabilities>
    <Tasks>
      <DefaultTask  Name ="_default" NavigationPage="MainPage.xaml"/>
    </Tasks>
    <Tokens>
      <PrimaryToken TokenID="PhoneApp1Token" TaskName="_default">
        <TemplateFlip>
          <SmallImageURI IsRelative="true" IsResource="false">Assets\Tiles\FlipCycleTileSmall.png</SmallImageURI>
          <Count>0</Count>
          <BackgroundImageURI IsRelative="true" IsResource="false">Assets\Tiles\FlipCycleTileMedium.png</BackgroundImageURI>
          <Title>StarWars_ListViewWithImages.WinPhone</Title>
          <BackContent></BackContent>
          <BackBackgroundImageURI></BackBackgroundImageURI>
          <BackTitle></BackTitle>
          <DeviceLockImageURI></DeviceLockImageURI>
          <HasLarge></HasLarge>
        </TemplateFlip>
      </PrimaryToken>
    </Tokens>
    <ScreenResolutions>
      <ScreenResolution Name="ID_RESOLUTION_WVGA"/>
      <ScreenResolution Name="ID_RESOLUTION_WXGA"/>
      <ScreenResolution Name="ID_RESOLUTION_HD720P"/>
    </ScreenResolutions>
  </App>
</Deployment>
